adafruit_circuitpython_tla202x-1.0.21.dist-info/licenses/LICENSE
adafruit_tla202x/__init__.py
adafruit_tla202x/analog_in.py
adafruit_tla202x/tla2024.py
adafruit_circuitpython_tla202x-1.0.21.dist-info/METADATA
adafruit_circuitpython_tla202x-1.0.21.dist-info/WHEEL
adafruit_circuitpython_tla202x-1.0.21.dist-info/top_level.txt
adafruit_circuitpython_tla202x-1.0.21.dist-info/RECORD
