Metadata-Version: 2.4
Name: adafruit-circuitpython-tla202x
Version: 1.0.21
Summary: Library for the TI TLA202x 12-bit ADCs
Author-email: Adafruit Industries <circuitpython@adafruit.com>
License: MIT
Project-URL: Homepage, https://github.com/adafruit/Adafruit_CircuitPython_TLA202x
Keywords: adafruit,blinka,circuitpython,micropython,tla202x,TLA2021,TLA2022,TLA2024,ADC,Delta-Sigma,Analog,Voltage
Classifier: Intended Audience :: Developers
Classifier: Topic :: Software Development :: Libraries
Classifier: Topic :: Software Development :: Embedded Systems
Classifier: Topic :: System :: Hardware
Classifier: License :: OSI Approved :: MIT License
Classifier: Programming Language :: Python :: 3
License-File: LICENSE
Requires-Dist: Adafruit-Blinka
Requires-Dist: adafruit-circuitpython-register
Requires-Dist: adafruit-circuitpython-busdevice
Provides-Extra: optional
Dynamic: license-file
